[
  {
    "login": "Emily-Jiang",
    "name": "Emily Jiang"
  },
  {
    "login": "KyleAure",
    "name": "Kyle Aure"
  },
  {
    "login": "OndroMih",
    "name": "Ondro Mihályi"
  },
  {
    "login": "Pandrex247",
    "name": "Andrew Pielage"
  },
  {
    "login": "alwin-joseph",
    "name": "Alwin Joseph"
  },
  {
    "login": "arjantijms",
    "name": "Arjan Tijms"
  },
  {
    "login": "aubi",
    "name": "Petr Aubrecht"
  },
  {
    "login": "autumnfound",
    "name": "Martin Lowe"
  },
  {
    "login": "cesarhernandezgt",
    "name": "Cesar Hernandez"
  },
  {
    "login": "chrisguindon",
    "name": "Christopher Guindon"
  },
  {
    "login": "edbratt",
    "name": "Ed Bratt"
  },
  {
    "login": "edburns",
    "name": "Ed Burns"
  },
  {
    "login": "ivargrimstad",
    "name": "Ivar Grimstad"
  },
  {
    "login": "jeanouii",
    "name": "Jean-Louis Monteiro"
  },
  {
    "login": "jim-krueger",
    "name": "Jim Krueger"
  },
  {
    "login": "kazumura",
    "name": "Kenji Kazumura"
  },
  {
    "login": "keilw",
    "name": "Werner Keil"
  },
  {
    "login": "laliwa",
    "name": "Eric.Meng@Primeton"
  },
  {
    "login": "linkfang",
    "name": "Zhou Fang"
  },
  {
    "login": "lukasj",
    "name": "Lukas Jungmann"
  },
  {
    "login": "m0mus",
    "name": "Dmitry Kornilov"
  },
  {
    "login": "manovotn",
    "name": "Matej Novotny"
  },
  {
    "login": "marceloancelmo",
    "name": "Marcelo Ancelmo"
  },
  {
    "login": "markt-asf",
    "name": "Mark Thomas"
  },
  {
    "login": "njr-11",
    "name": "Nathan Rauh"
  },
  {
    "login": "oliviergoulet5",
    "name": "Olivier Goulet"
  },
  {
    "login": "otaviojava",
    "name": "Otávio Santana"
  },
  {
    "login": "scottkurz",
    "name": "Scott Kurz"
  },
  {
    "login": "scottmarlow",
    "name": "Scott Marlow"
  },
  {
    "login": "spericas",
    "name": "Santiago Pericas-Geertsen"
  },
  {
    "login": "starksm64",
    "name": "Scott M Stark"
  },
  {
    "login": "tjwatson",
    "name": "Thomas Watson"
  },
  {
    "login": "waynebeaton",
    "name": "Wayne Beaton"
  }
]
